Metadata-Version: 2.1
Name: deepnpg
Version: 0.0.2
Summary: Python library for building preconditiioner with Graph Neural Networks
Home-page: https://github.com/inEXASCALE/deepnpc.git
Author: Xinye Chen
Author-email: xinyechenai@gmail.com
License: MIT License
Classifier: Intended Audience :: Science/Research
Classifier: Intended Audience :: Developers
Classifier: Programming Language :: C
Classifier: Programming Language :: Python
Classifier: Topic :: Software Development
Classifier: Topic :: Scientific/Engineering
Classifier: Operating System :: Microsoft :: Windows
Classifier: Operating System :: POSIX
Classifier: Operating System :: Unix
Classifier: Operating System :: MacOS
Classifier: Programming Language :: Python :: 3
License-File: LICENSE
Requires-Dist: numpy>=1.17.3
Requires-Dist: scipy>=1.7.0
Requires-Dist: matplotlib>=3.5
Requires-Dist: torch
Requires-Dist: torch_geometric
Requires-Dist: requests
